async_http_client/__init__.py
async_http_client/client.py
async_http_client/constants.py
async_http_client/exceptions.py
async_http_client/response.py
async_http_client/validators.py
async_api_client-0.0.2.dist-info/METADATA
async_api_client-0.0.2.dist-info/WHEEL
async_api_client-0.0.2.dist-info/top_level.txt
async_api_client-0.0.2.dist-info/RECORD
